{
  "parent": "minecraft:husbandry/get_porcelain_bricks",
  "display": {
    "icon": {
      "item": "betterclay:chiseled_earthenware_bricks"
    },
    "title": {
      "translate": "advancements.husbandry.get_earthenware_bricks.title"
    },
    "description": {
      "translate": "advancements.husbandry.get_earthenware_bricks.description"
    },
    "frame": "task",
    "show_toast": true,
    "announce_to_chat": true,
    "hidden": false
  },
  "criteria": {
    "earthenware_bricks": {
      "trigger": "minecraft:inventory_changed",
      "conditions": {
        "items": [
          {
            "item": "betterclay:earthenware_bricks"
          }
        ]
      }
    }
  },
  "requirements": [
    [
      "earthenware_bricks"
    ]
  ]
}